[{"id": 397212500, "node_id": "MDEwOlJlcG9zaXRvcnkzOTcyMTI1MDA=", "name": "python", "full_name": "AlexeyAlpatov/python", "private": false, "owner": {"login": "AlexeyAlpatov", "id": 89076218, "node_id": "MDQ6VXNlcjg5MDc2MjE4", "avatar_url": "https://avatars.githubusercontent.com/u/89076218?v=4", "gravatar_id": "", "url": "https://api.github.com/users/AlexeyAlpatov", "html_url": "https://github.com/AlexeyAlpatov", "followers_url": "https://api.github.com/users/AlexeyAlpatov/followers", "following_url": "https://api.github.com/users/AlexeyAlpatov/following{/other_user}", "gists_url": "https://api.github.com/users/AlexeyAlpatov/gists{/gist_id}", "starred_url": "https://api.github.com/users/AlexeyAlpatov/starred{/owner}{/repo}", "subscriptions_url": "https://api.github.com/users/AlexeyAlpatov/subscriptions", "organizations_url": "https://api.github.com/users/AlexeyAlpatov/orgs", "repos_url": "https://api.github.com/users/AlexeyAlpatov/repos", "events_url": "https://api.github.com/users/AlexeyAlpatov/events{/privacy}", "received_events_url": "https://api.github.com/users/AlexeyAlpatov/received_events", "type": "User", "site_admin": false}, "html_url": "https://github.com/AlexeyAlpatov/python", "description": null, "fork": false, "url": "https://api.github.com/repos/AlexeyAlpatov/python", "forks_url": "https://api.github.com/repos/AlexeyAlpatov/python/forks", "keys_url": "https://api.github.com/repos/AlexeyAlpatov/python/keys{/key_id}", "collaborators_url": "https://api.github.com/repos/AlexeyAlpatov/python/collaborators{/collaborator}", "teams_url": "https://api.github.com/repos/AlexeyAlpatov/python/teams", "hooks_url": "https://api.github.com/repos/AlexeyAlpatov/python/hooks", "issue_events_url": "https://api.github.com/repos/AlexeyAlpatov/python/issues/events{/number}", "events_url": "https://api.github.com/repos/AlexeyAlpatov/python/events", "assignees_url": "https://api.github.com/repos/AlexeyAlpatov/python/assignees{/user}", "branches_url": "https://api.github.com/repos/AlexeyAlpatov/python/branches{/branch}", "tags_url": "https://api.github.com/repos/AlexeyAlpatov/python/tags", "blobs_url": "https://api.github.com/repos/AlexeyAlpatov/python/git/blobs{/sha}", "git_tags_url": "https://api.github.com/repos/AlexeyAlpatov/python/git/tags{/sha}", "git_refs_url": "https://api.github.com/repos/AlexeyAlpatov/python/git/refs{/sha}", "trees_url": "https://api.github.com/repos/AlexeyAlpatov/python/git/trees{/sha}", "statuses_url": "https://api.github.com/repos/AlexeyAlpatov/python/statuses/{sha}", "languages_url": "https://api.github.com/repos/AlexeyAlpatov/python/languages", "stargazers_url": "https://api.github.com/repos/AlexeyAlpatov/python/stargazers", "contributors_url": "https://api.github.com/repos/AlexeyAlpatov/python/contributors", "subscribers_url": "https://api.github.com/repos/AlexeyAlpatov/python/subscribers", "subscription_url": "https://api.github.com/repos/AlexeyAlpatov/python/subscription", "commits_url": "https://api.github.com/repos/AlexeyAlpatov/python/commits{/sha}", "git_commits_url": "https://api.github.com/repos/AlexeyAlpatov/python/git/commits{/sha}", "comments_url": "https://api.github.com/repos/AlexeyAlpatov/python/comments{/number}", "issue_comment_url": "https://api.github.com/repos/AlexeyAlpatov/python/issues/comments{/number}", "contents_url": "https://api.github.com/repos/AlexeyAlpatov/python/contents/{+path}", "compare_url": "https://api.github.com/repos/AlexeyAlpatov/python/compare/{base}...{head}", "merges_url": "https://api.github.com/repos/AlexeyAlpatov/python/merges", "archive_url": "https://api.github.com/repos/AlexeyAlpatov/python/{archive_format}{/ref}", "downloads_url": "https://api.github.com/repos/AlexeyAlpatov/python/downloads", "issues_url": "https://api.github.com/repos/AlexeyAlpatov/python/issues{/number}", "pulls_url": "https://api.github.com/repos/AlexeyAlpatov/python/pulls{/number}", "milestones_url": "https://api.github.com/repos/AlexeyAlpatov/python/milestones{/number}", "notifications_url": "https://api.github.com/repos/AlexeyAlpatov/python/notifications{?since,all,participating}", "labels_url": "https://api.github.com/repos/AlexeyAlpatov/python/labels{/name}", "releases_url": "https://api.github.com/repos/AlexeyAlpatov/python/releases{/id}", "deployments_url": "https://api.github.com/repos/AlexeyAlpatov/python/deployments", "created_at": "2021-08-17T10:37:24Z", "updated_at": "2021-08-28T09:21:41Z", "pushed_at": "2021-09-23T11:17:24Z", "git_url": "git://github.com/AlexeyAlpatov/python.git", "ssh_url": "git@github.com:AlexeyAlpatov/python.git", "clone_url": "https://github.com/AlexeyAlpatov/python.git", "svn_url": "https://github.com/AlexeyAlpatov/python", "homepage": null, "size": 24, "stargazers_count": 0, "watchers_count": 0, "language": null, "has_issues": true, "has_projects": true, "has_downloads": true, "has_wiki": true, "has_pages": false, "forks_count": 0, "mirror_url": null, "archived": false, "disabled": false, "open_issues_count": 8, "license": null, "allow_forking": true, "is_template": false, "topics": [], "visibility": "public", "forks": 0, "open_issues": 8, "watchers": 0, "default_branch": "main"}, {"id": 459438491, "node_id": "R_kgDOG2J5mw", "name": "Python_API", "full_name": "AlexeyAlpatov/Python_API", "private": false, "owner": {"login": "AlexeyAlpatov", "id": 89076218, "node_id": "MDQ6VXNlcjg5MDc2MjE4", "avatar_url": "https://avatars.githubusercontent.com/u/89076218?v=4", "gravatar_id": "", "url": "https://api.github.com/users/AlexeyAlpatov", "html_url": "https://github.com/AlexeyAlpatov", "followers_url": "https://api.github.com/users/AlexeyAlpatov/followers", "following_url": "https://api.github.com/users/AlexeyAlpatov/following{/other_user}", "gists_url": "https://api.github.com/users/AlexeyAlpatov/gists{/gist_id}", "starred_url": "https://api.github.com/users/AlexeyAlpatov/starred{/owner}{/repo}", "subscriptions_url": "https://api.github.com/users/AlexeyAlpatov/subscriptions", "organizations_url": "https://api.github.com/users/AlexeyAlpatov/orgs", "repos_url": "https://api.github.com/users/AlexeyAlpatov/repos", "events_url": "https://api.github.com/users/AlexeyAlpatov/events{/privacy}", "received_events_url": "https://api.github.com/users/AlexeyAlpatov/received_events", "type": "User", "site_admin": false}, "html_url": "https://github.com/AlexeyAlpatov/Python_API", "description": null, "fork": false, "url": "https://api.github.com/repos/AlexeyAlpatov/Python_API", "forks_url": "https://api.github.com/repos/AlexeyAlpatov/Python_API/forks", "keys_url": "https://api.github.com/repos/AlexeyAlpatov/Python_API/keys{/key_id}", "collaborators_url": "https://api.github.com/repos/AlexeyAlpatov/Python_API/collaborators{/collaborator}", "teams_url": "https://api.github.com/repos/AlexeyAlpatov/Python_API/teams", "hooks_url": "https://api.github.com/repos/AlexeyAlpatov/Python_API/hooks", "issue_events_url": "https://api.github.com/repos/AlexeyAlpatov/Python_API/issues/events{/number}", "events_url": "https://api.github.com/repos/AlexeyAlpatov/Python_API/events", "assignees_url": "https://api.github.com/repos/AlexeyAlpatov/Python_API/assignees{/user}", "branches_url": "https://api.github.com/repos/AlexeyAlpatov/Python_API/branches{/branch}", "tags_url": "https://api.github.com/repos/AlexeyAlpatov/Python_API/tags", "blobs_url": "https://api.github.com/repos/AlexeyAlpatov/Python_API/git/blobs{/sha}", "git_tags_url": "https://api.github.com/repos/AlexeyAlpatov/Python_API/git/tags{/sha}", "git_refs_url": "https://api.github.com/repos/AlexeyAlpatov/Python_API/git/refs{/sha}", "trees_url": "https://api.github.com/repos/AlexeyAlpatov/Python_API/git/trees{/sha}", "statuses_url": "https://api.github.com/repos/AlexeyAlpatov/Python_API/statuses/{sha}", "languages_url": "https://api.github.com/repos/AlexeyAlpatov/Python_API/languages", "stargazers_url": "https://api.github.com/repos/AlexeyAlpatov/Python_API/stargazers", "contributors_url": "https://api.github.com/repos/AlexeyAlpatov/Python_API/contributors", "subscribers_url": "https://api.github.com/repos/AlexeyAlpatov/Python_API/subscribers", "subscription_url": "https://api.github.com/repos/AlexeyAlpatov/Python_API/subscription", "commits_url": "https://api.github.com/repos/AlexeyAlpatov/Python_API/commits{/sha}", "git_commits_url": "https://api.github.com/repos/AlexeyAlpatov/Python_API/git/commits{/sha}", "comments_url": "https://api.github.com/repos/AlexeyAlpatov/Python_API/comments{/number}", "issue_comment_url": "https://api.github.com/repos/AlexeyAlpatov/Python_API/issues/comments{/number}", "contents_url": "https://api.github.com/repos/AlexeyAlpatov/Python_API/contents/{+path}", "compare_url": "https://api.github.com/repos/AlexeyAlpatov/Python_API/compare/{base}...{head}", "merges_url": "https://api.github.com/repos/AlexeyAlpatov/Python_API/merges", "archive_url": "https://api.github.com/repos/AlexeyAlpatov/Python_API/{archive_format}{/ref}", "downloads_url": "https://api.github.com/repos/AlexeyAlpatov/Python_API/downloads", "issues_url": "https://api.github.com/repos/AlexeyAlpatov/Python_API/issues{/number}", "pulls_url": "https://api.github.com/repos/AlexeyAlpatov/Python_API/pulls{/number}", "milestones_url": "https://api.github.com/repos/AlexeyAlpatov/Python_API/milestones{/number}", "notifications_url": "https://api.github.com/repos/AlexeyAlpatov/Python_API/notifications{?since,all,participating}", "labels_url": "https://api.github.com/repos/AlexeyAlpatov/Python_API/labels{/name}", "releases_url": "https://api.github.com/repos/AlexeyAlpatov/Python_API/releases{/id}", "deployments_url": "https://api.github.com/repos/AlexeyAlpatov/Python_API/deployments", "created_at": "2022-02-15T05:20:30Z", "updated_at": "2022-02-15T05:20:30Z", "pushed_at": "2022-02-15T05:20:30Z", "git_url": "git://github.com/AlexeyAlpatov/Python_API.git", "ssh_url": "git@github.com:AlexeyAlpatov/Python_API.git", "clone_url": "https://github.com/AlexeyAlpatov/Python_API.git", "svn_url": "https://github.com/AlexeyAlpatov/Python_API", "homepage": null, "size": 0, "stargazers_count": 0, "watchers_count": 0, "language": null, "has_issues": true, "has_projects": true, "has_downloads": true, "has_wiki": true, "has_pages": false, "forks_count": 0, "mirror_url": null, "archived": false, "disabled": false, "open_issues_count": 0, "license": null, "allow_forking": true, "is_template": false, "topics": [], "visibility": "public", "forks": 0, "open_issues": 0, "watchers": 0, "default_branch": "main"}]